{
	"backtrace" : 0,
	"backtraceGraph" : 
	{
		"commands" : [],
		"files" : 
		[
			"Libraries/game/CMakeLists.txt"
		],
		"nodes" : 
		[
			{
				"file" : 0
			}
		]
	},
	"id" : "game_autogen_timestamp_deps::@099bcd863ccdebebf6b8",
	"isGeneratorProvided" : true,
	"name" : "game_autogen_timestamp_deps",
	"paths" : 
	{
		"build" : "Libraries/game",
		"source" : "Libraries/game"
	},
	"sourceGroups" : 
	[
		{
			"name" : "",
			"sourceIndexes" : 
			[
				0
			]
		},
		{
			"name" : "CMake Rules",
			"sourceIndexes" : 
			[
				1
			]
		}
	],
	"sources" : 
	[
		{
			"backtrace" : 0,
			"isGenerated" : true,
			"path" : "build/Qt_6_7_0_for_macOS-Debug/Libraries/game/CMakeFiles/game_autogen_timestamp_deps",
			"sourceGroupIndex" : 0
		},
		{
			"backtrace" : 0,
			"isGenerated" : true,
			"path" : "build/Qt_6_7_0_for_macOS-Debug/Libraries/game/CMakeFiles/game_autogen_timestamp_deps.rule",
			"sourceGroupIndex" : 1
		}
	],
	"type" : "UTILITY"
}
